opinion_clob_sdk/__init__.py
opinion_clob_sdk/builder_sdk.py
opinion_clob_sdk/config.py
opinion_clob_sdk/model.py
opinion_clob_sdk/sdk.py
opinion_clob_sdk/user_client.py
opinion_clob_sdk/verify_api_calls.py
opinion_clob_sdk/verify_checksum_addresses.py
opinion_clob_sdk/websocket_client.py
opinion_clob_sdk/websocket_models.py
opinion_clob_sdk/chain/__init__.py
opinion_clob_sdk/chain/contract_caller.py
opinion_clob_sdk/chain/exception.py
opinion_clob_sdk/chain/contracts/__init__.py
opinion_clob_sdk/chain/contracts/conditional_tokens.py
opinion_clob_sdk/chain/contracts/erc20.py
opinion_clob_sdk/chain/py_order_utils/__init__.py
opinion_clob_sdk/chain/py_order_utils/constants.py
opinion_clob_sdk/chain/py_order_utils/signer.py
opinion_clob_sdk/chain/py_order_utils/utils.py
opinion_clob_sdk/chain/py_order_utils/abi/Exchange.json
opinion_clob_sdk/chain/py_order_utils/abi/FeeManager.json
opinion_clob_sdk/chain/py_order_utils/abi/FeeManager.py
opinion_clob_sdk/chain/py_order_utils/builders/__init__.py
opinion_clob_sdk/chain/py_order_utils/builders/base_builder.py
opinion_clob_sdk/chain/py_order_utils/builders/exception.py
opinion_clob_sdk/chain/py_order_utils/builders/order_builder.py
opinion_clob_sdk/chain/py_order_utils/builders/order_builder_test.py
opinion_clob_sdk/chain/py_order_utils/model/__init__.py
opinion_clob_sdk/chain/py_order_utils/model/order.py
opinion_clob_sdk/chain/py_order_utils/model/order_type.py
opinion_clob_sdk/chain/py_order_utils/model/sides.py
opinion_clob_sdk/chain/py_order_utils/model/signatures.py
opinion_clob_sdk/chain/safe/__init__.py
opinion_clob_sdk/chain/safe/constants.py
opinion_clob_sdk/chain/safe/enums.py
opinion_clob_sdk/chain/safe/exceptions.py
opinion_clob_sdk/chain/safe/multisend.py
opinion_clob_sdk/chain/safe/safe.py
opinion_clob_sdk/chain/safe/safe_signature.py
opinion_clob_sdk/chain/safe/safe_test.py
opinion_clob_sdk/chain/safe/safe_tx.py
opinion_clob_sdk/chain/safe/safe_tx_builder.py
opinion_clob_sdk/chain/safe/signatures.py
opinion_clob_sdk-0.6.0.dist-info/METADATA
opinion_clob_sdk-0.6.0.dist-info/WHEEL
opinion_clob_sdk-0.6.0.dist-info/top_level.txt
opinion_clob_sdk-0.6.0.dist-info/RECORD
