Metadata-Version: 2.4
Name: opinion_clob_sdk
Version: 0.6.0
Summary: Opinion CLOB SDK (Tech Preview) - Python SDK for Opinion Prediction Market Central Limit Order Book API
Home-page: https://opinion.trade
Author: Opinion Labs
Author-email: support@opinion.trade
Keywords: PredictionMarket,CLOB,Trading,Blockchain,BNBChain,BSC,Opinion
Classifier: Development Status :: 5 - Production/Stable
Classifier: Intended Audience :: Developers
Classifier: Topic :: Software Development :: Libraries :: Python Modules
Classifier: License :: OSI Approved :: MIT License
Classifier: Programming Language :: Python :: 3
Classifier: Programming Language :: Python :: 3.9
Classifier: Programming Language :: Python :: 3.10
Classifier: Programming Language :: Python :: 3.11
Classifier: Programming Language :: Python :: 3.12
Requires-Python: >=3.9.10
Requires-Dist: urllib3>=2.3.0
Requires-Dist: six>=1.17.0
Requires-Dist: certifi>=2024.12.14
Requires-Dist: python-dateutil>=2.9.0.post0
Requires-Dist: hexbytes>=1.2.1
Requires-Dist: web3>=7.6.1
Requires-Dist: eth_account>=0.13.0
Requires-Dist: poly_eip712_structs>=0.0.1
Requires-Dist: opinion_api>=0.3.0
Requires-Dist: websocket-client>=1.6.0
Requires-Dist: pytest>=7.0.0
Dynamic: author
Dynamic: author-email
Dynamic: classifier
Dynamic: description
Dynamic: description-content-type
Dynamic: home-page
Dynamic: keywords
Dynamic: requires-dist
Dynamic: requires-python
Dynamic: summary
